sshkey_tools/__init__.py
sshkey_tools/__version__.py
sshkey_tools/cert.py
sshkey_tools/exceptions.py
sshkey_tools/fields.py
sshkey_tools/keys.py
sshkey_tools/utils.py
sshkey_tools-0.11.3.dist-info/LICENSE
sshkey_tools-0.11.3.dist-info/METADATA
sshkey_tools-0.11.3.dist-info/WHEEL
sshkey_tools-0.11.3.dist-info/entry_points.txt
sshkey_tools-0.11.3.dist-info/top_level.txt
sshkey_tools-0.11.3.dist-info/zip-safe
sshkey_tools-0.11.3.dist-info/RECORD
