Metadata-Version: 2.1
Name: sshkey-tools
Version: 0.11.3
Summary: A Python module for generating, parsing and handling OpenSSH keys and certificates
Home-page: https://github.com/scheiblingco/sshkey-tools
Author: Lars Scheibling
Author-email: lars@scheibling.se
License: GnuPG 3.0
Keywords: python openssh ssh keys sshkey ssh-keygen ssh-certificate certificate parser decoder
Classifier: Programming Language :: Python :: 3
Classifier: License :: OSI Approved :: GNU General Public License v3 (GPLv3)
Classifier: Operating System :: OS Independent
Requires-Python: >=3.6
License-File: LICENSE
Requires-Dist: click~=8.1
Requires-Dist: cryptography<44,>=42.0
Requires-Dist: bcrypt~=4.2
Requires-Dist: PrettyTable~=3.9
Requires-Dist: pytimeparse2~=1.1
